django_formify/__init__.py
django_formify/app_settings.py
django_formify/apps.py
django_formify/components/formify/tw/field_error.html
django_formify/components/formify/tw/field_error.py
django_formify/components/formify/tw/field_error_help_text.html
django_formify/components/formify/tw/field_error_help_text.py
django_formify/components/formify/tw/field_help_text.html
django_formify/components/formify/tw/field_help_text.py
django_formify/components/formify/tw/field_label.html
django_formify/components/formify/tw/field_label.py
django_formify/components/formify/tw/field_wrapper.html
django_formify/components/formify/tw/field_wrapper.py
django_formify/tailwind/__init__.py
django_formify/tailwind/formify_helper.py
django_formify/tailwind/layout.py
django_formify/templates/formify/tailwind/attrs.html
django_formify/templates/formify/tailwind/checkbox_input.html
django_formify/templates/formify/tailwind/checkbox_select_multiple.html
django_formify/templates/formify/tailwind/common_field.html
django_formify/templates/formify/tailwind/components/button.html
django_formify/templates/formify/tailwind/components/div.html
django_formify/templates/formify/tailwind/components/fieldset.html
django_formify/templates/formify/tailwind/errors.html
django_formify/templates/formify/tailwind/errors_formset.html
django_formify/templates/formify/tailwind/file_input.html
django_formify/templates/formify/tailwind/form_tag.html
django_formify/templates/formify/tailwind/radio_select.html
django_formify/templates/formify/tailwind/select.html
django_formify/templates/formify/tailwind/select_option.html
django_formify/templatetags/formify.py
django_formify/utils.py
django_formify-0.0.8.dist-info/METADATA
django_formify-0.0.8.dist-info/WHEEL
django_formify-0.0.8.dist-info/RECORD
