Metadata-Version: 2.3
Name: django-formify
Version: 0.0.8
Summary: Django-Formify seamlessly integrates Tailwind CSS styles into your Django forms for a modern look.
License: MIT
Author: Michael Yin
Author-email: michaelyin@accordbox.com
Requires-Python: >=3.8
Classifier: License :: OSI Approved :: MIT License
Classifier: Programming Language :: Python :: 3
Classifier: Programming Language :: Python :: 3.8
Classifier: Programming Language :: Python :: 3.9
Classifier: Programming Language :: Python :: 3.10
Classifier: Programming Language :: Python :: 3.11
Classifier: Programming Language :: Python :: 3.12
Classifier: Programming Language :: Python :: 3.13
Requires-Dist: django (>=3.0)
Requires-Dist: django-viewcomponent (>=1.0.8)
Project-URL: Changelog, https://github.com/rails-inspire-django/django-formify/releases
Project-URL: Homepage, https://github.com/rails-inspire-django/django-formify
